examples/analog_input.py
examples/analog_input2.py
examples/blink.py
examples/dht.py
examples/digital_input_pullup.py
examples/fade.py
examples/get_pico_pins.py
examples/hc_sr04.py
examples/i2c_adxl345_accelerometer.py
examples/loop_back.py
examples/neopixels.py
examples/servo.py
examples/spi_mpu9250.py
examplesSAVE/analog_input.py
examplesSAVE/dht.py
examplesSAVE/digital_input_pullup.py
examplesSAVE/fade.py
examplesSAVE/hc-sr04_distance_sensor.py
examplesSAVE/i2c_adxl345_accelerometer.py
examplesSAVE/servo.py
resources/private_constants.py
resources/telemetrix_aio.py
resources/telemetrix_rpi_pico.py
resources/telemtrix_aio_serial.py
tmx_pico_aio/__init__.py
tmx_pico_aio/private_constants.py
tmx_pico_aio/telemtrix_aio_serial.py
tmx_pico_aio/tmx_pico_aio.py
venv/bin/activate_this.py
venv2/bin/activate_this.py
tmx_pico_aio-1.5.1.dist-info/METADATA
tmx_pico_aio-1.5.1.dist-info/WHEEL
tmx_pico_aio-1.5.1.dist-info/top_level.txt
tmx_pico_aio-1.5.1.dist-info/RECORD
