Metadata-Version: 2.4
Name: tmx-pico-aio
Version: 1.5.1
Summary: Telemetrix Asyncio Client For The Raspberry Pi Pico
Author-email: Alan Yorinks <MisterYsLab@gmail.com>
License: AGPL-3.0-or-later
Project-URL: Homepage, https://github.com/MrYsLab/tmx-pico-aio
Project-URL: Issues, https://github.com/MrYsLab/tmx-pico-aio/issues
Keywords: telemetrix,asnyncio,Arduino,rp2040,Pico,Python
Classifier: Development Status :: 5 - Production/Stable
Classifier: Environment :: Other Environment
Classifier: Intended Audience :: Developers
Classifier: Intended Audience :: Education
Classifier: Operating System :: OS Independent
Classifier: Topic :: Software Development :: Libraries :: Python Modules
Requires-Python: >=3.8
Requires-Dist: pyserial
